myodbc/__init__.py
myodbc/myodbc.py
myodbc_fr8train-1.1.0.dist-info/licenses/LICENSE
myodbc_fr8train-1.1.0.dist-info/METADATA
myodbc_fr8train-1.1.0.dist-info/WHEEL
myodbc_fr8train-1.1.0.dist-info/top_level.txt
myodbc_fr8train-1.1.0.dist-info/RECORD
