Metadata-Version: 2.4
Name: myodbc-fr8train
Version: 1.1.0
Summary: Refactoring of typical ODBC handling for myodbcSQL18
Author-email: Tyler Collette <tyler.collette@gmail.com>
Project-URL: Documentation, https://github.com/fr8train-sv/myodbc
Project-URL: Source, https://github.com/fr8train-sv/myodbc
Project-URL: Changelog, https://github.com/fr8train-sv/myodbc/releases
Keywords: myodbc,18,fr8train
Classifier: Programming Language :: Python :: 3
Classifier: Programming Language :: Python :: 3.12
Classifier: Operating System :: OS Independent
License-File: LICENSE
Requires-Dist: dotenv
Requires-Dist: pyodbc
Requires-Dist: python-dotenv
Dynamic: license-file
